{"authorDailyContributionsMap":{"thant":[{"date":"2023-03-02","commitResults":[{"hash":"7b9bd8019bdb20caf75109cb1652c25186427e6c","isMergeCommit":false,"messageTitle":"Update README.md","messageBody":"","fileTypesAndContributionMap":{"docs":{"insertions":6,"deletions":63}}}]},{"date":"2023-03-09","commitResults":[{"hash":"27f4481a67889330d64884e409101f1359be4f73","isMergeCommit":true,"messageTitle":"Merge pull request #1 from jeraldgau/master","messageBody":"Base code for Duck","fileTypesAndContributionMap":{}}]},{"date":"2023-03-11","commitResults":[{"hash":"14324e6e0451447948a7e5310896732b793ed89e","isMergeCommit":true,"messageTitle":"Merge pull request #1 from AY2223S2-CS2113-T11-1/master","messageBody":"pulling","fileTypesAndContributionMap":{}},{"hash":"365cd2a2cbd4566b0bec265a3a351999a1dd1459","isMergeCommit":false,"messageTitle":"Added date time tracking for Duck inputs","messageBody":"","fileTypesAndContributionMap":{"functional-code":{"insertions":95,"deletions":32}}},{"hash":"8e2bc1442b03e26852bc4712c01f97d7be07014f","isMergeCommit":true,"messageTitle":"Merge pull request #4 from thant/master","messageBody":"Date time tracking + help function added","fileTypesAndContributionMap":{}}]}],"miahjerry":[],"jeraldgau":[{"date":"2023-03-09","commitResults":[{"hash":"2d7d6f2d46a92b659abb6088a04044f407379941","isMergeCommit":false,"messageTitle":"Copy over from iP to serve as base code for Duck","messageBody":"","fileTypesAndContributionMap":{"functional-code":{"insertions":770,"deletions":21}}},{"hash":"0d5a591414a6268df65f4d955a663f8e8cd6fd89","isMergeCommit":false,"messageTitle":"Changed class and file names to Duck","messageBody":"","fileTypesAndContributionMap":{"other":{"insertions":30,"deletions":30}}},{"hash":"948b17596890624ec5fd7a35ca7bf960e899b954","isMergeCommit":false,"messageTitle":"Fixed a bug causing an error message to be shown when string input is given where an integer input is expected in the user command.","messageBody":"","fileTypesAndContributionMap":{"functional-code":{"insertions":2,"deletions":1}}},{"hash":"6b986d0ec21c35f0c3e35240d79baf1af7ed5ce9","isMergeCommit":false,"messageTitle":"Fixed checkstyle errors","messageBody":"","fileTypesAndContributionMap":{"functional-code":{"insertions":7,"deletions":7}}},{"hash":"61ffd5f78f8fde0eca9563278b3d0a68606e0dc7","isMergeCommit":false,"messageTitle":"Changed README back to the original text","messageBody":"Previously changed README to have changed files to compare with main repo, changing the README back for easier reference.","fileTypesAndContributionMap":{"docs":{"insertions":63,"deletions":6}}},{"hash":"4ebe339bdaeb53f80ee5242f8e7f24c8c300f58a","isMergeCommit":true,"messageTitle":"Merge pull request #3 from jeraldgau/master","messageBody":"Changed README back to the original text","fileTypesAndContributionMap":{}}]}],"MichelleLiang0116":[],"skyanzy":[]},"authorFileTypeContributionMap":{"thant":{"docs":0,"functional-code":95,"test-code":0},"miahjerry":{"docs":0,"functional-code":0,"test-code":0},"jeraldgau":{"docs":50,"functional-code":739,"test-code":2},"MichelleLiang0116":{"docs":0,"functional-code":0,"test-code":0},"skyanzy":{"docs":0,"functional-code":0,"test-code":0}},"authorContributionVariance":{"thant":835.64087,"miahjerry":0.0,"jeraldgau":36512.887,"MichelleLiang0116":0.0,"skyanzy":0.0},"authorDisplayNameMap":{"thant":"CS2113-T11-1 THAN..NYAN","miahjerry":"CS2113-T11-1 ONG ..MIAH","jeraldgau":"CS2113-T11-1 GAU ..RALD","MichelleLiang0116":"CS2113-T11-1 LIAN..G-YU","skyanzy":"CS2113-T11-1 YAN ..AIYA"}}
